drf_simple_access_key/__init__.py
drf_simple_access_key/permissions.py
drf_simple_access_key/settings.py
drf_simple_access_key-1.1.0.dist-info/LICENSE
drf_simple_access_key-1.1.0.dist-info/METADATA
drf_simple_access_key-1.1.0.dist-info/WHEEL
drf_simple_access_key-1.1.0.dist-info/top_level.txt
drf_simple_access_key-1.1.0.dist-info/RECORD
