Metadata-Version: 2.1
Name: drf-simple-access-key
Version: 1.1.0
Summary: A library that provides a simple token authorization for Django REST framework.
Home-page: https://github.com/anexia/drf-simple-access-key
Author: Harald Nezbeda
Author-email: HNezbeda@anexia-it.com
License: MIT
Classifier: License :: OSI Approved :: MIT License
Classifier: Framework :: Django
Classifier: Framework :: Django :: 4.2
Classifier: Framework :: Django :: 5.0
Classifier: Framework :: Django :: 5.1
Classifier: Programming Language :: Python
Classifier: Programming Language :: Python :: 3
Classifier: Programming Language :: Python :: 3.9
Classifier: Programming Language :: Python :: 3.10
Classifier: Programming Language :: Python :: 3.11
Classifier: Programming Language :: Python :: 3.12
Classifier: Programming Language :: Python :: 3.13
Classifier: Programming Language :: Python :: Implementation :: CPython
Classifier: Programming Language :: Python :: Implementation :: PyPy
License-File: LICENSE
Requires-Dist: django>=4.2
Requires-Dist: djangorestframework>=3.15
